Workbook

Sheet Estados Financieros (Datos)
A1: COMERCIALIZADORA INDUSTRIAL LOS ANDES, C.A.
A2: Cuestionario y Datos de Trabajo | Módulo 10: Análisis de la Contabilidad (UCSAR - Prof. MSc. Frank Clemente)
A4: 1. ESTADO DE SITUACIÓN FINANCIERA (BALANCE GENERAL) COMPARATIVO
A5: Código / Cuenta Patrimonial | B5: Año 1 (BS) | C5: Año 2 (BS) | D5: Pasivos y Patrimonio | E5: Año 1 (BS) | F5: Año 2 (BS)
A6: Efectivo y Equivalentes | B6: 45000 | C6: 5000 | D6: Cuentas por Pagar Proveedores | E6: 60000 | F6: 180000
A7: Cuentas por Cobrar (Neto) | B7: 80000 | C7: 250000 | D7: Gastos Acumulados por Pagar | E7: 15000 | F7: 45000
A8: Inventarios | B8: 120000 | C8: 320000 | D8: Préstamos Bancarios Corto Plazo | E8: 25000 | F8: 50000
A9: TOTAL ACTIVO CORRIENTE | B9: 245000 | C9: 575000 | D9: TOTAL PASIVO CORRIENTE | E9: 100000 | F9: 275000
A11: Terrenos y Edificios (Neto) | B11: 300000 | C11: 290000 | D11: Préstamos Bancarios Largo Plazo | E11: 150000 | F11: 120000
A12: Maquinaria y Equipos (Neto) | B12: 180000 | C12: 165000 | D12: TOTAL PASIVO NO CORRIENTE | E12: 150000 | F12: 120000
A13: TOTAL ACTIVO NO CORRIENTE | B13: 480000 | C13: 455000 | D13: TOTAL PASIVO | E13: 250000 | F13: 395000
D15: Capital Social | E15: 300000 | F15: 300000
D16: Reservas Legales | E16: 25000 | F16: 35000
D17: Utilidades Retenidas | E17: 150000 | F17: 300000
D18: TOTAL PATRIMONIO | E18: 475000 | F18: 635000
A19: TOTAL ACTIVO | B19: 725000 | C19: 1030000 | D19: TOTAL PASIVO + PATRIMONIO | E19: 725000 | F19: 1030000
A22: 2. ESTADO DE RESULTADOS INTEGRAL COMPARATIVO
A23: Concepto Económico | B23: Año 1 (BS) | C23: Año 2 (BS)
A24: Ventas Netas Totales | B24: 1000000 | C24: 1400000
A25: Costo de Ventas | B25: -600000 | C25: -850000
A26: MARGEN BRUTO EN VENTAS | B26: 400000 | C26: 550000
A27: Gastos Operativos (Ventas y Administración) | B27: -220000 | C27: -310000
A28: Gastos por Depreciación | B28: -30000 | C28: -35000
A29: UTILIDAD OPERATIVA (EBIT) | B29: 150000 | C29: 205000
A30: Gastos Financieros (Intereses) | B30: -20000 | C30: -25000
A31: UTILIDAD ANTES DE IMPUESTOS (EBT) | B31: 130000 | C31: 180000
A32: Impuesto Sobre la Renta (ISLR - 30%) | B32: -39000 | C32: -54000
A33: UTILIDAD NETA DEL EJERCICIO | B33: 91000 | C33: 126000
A35: 3. DATOS ADICIONALES PARA PUNTO DE EQUILIBRIO Y COSTOS (AÑO 2)
A36: Gastos Operativos Fijos Totales (Alquileres, sueldos fijos, servicios) | B36: 210000 | C36: BS
A37: Gastos Operativos Variables Totales (Comisiones, empaques, fletes) | B37: 100000 | C37: BS
A38: Volumen Físico de Ventas (Unidades comercializadas en Año 2) | B38: 12727 | C38: Unidades
A39: Precio Promedio de Venta Unitario (PVU en Año 2) | B39: 110 | C39: BS/Unidad

Sheet Plantilla Trabajo Estudiante
A1: PLANTILLA DE TRABAJO PRÁCTICO PARA EL ESTUDIANTE
A2: Complete las celdas amarillas aplicando las fórmulas del Módulo 10.
A4: UNIDAD 1: ANÁLISIS VERTICAL Y HORIZONTAL DE ACTIVOS
A5: Cuenta de Activo | B5: Año 1 (BS) | C5: Año 2 (BS) | D5: % Vertical (Año 2) | E5: Δ Absoluta (BS) | F5: % Variación Horizontal
A6: Efectivo y Equivalentes | B6: ='Estados Financieros (Datos)'!B6 | C6: ='Estados Financieros (Datos)'!C6
A7: Cuentas por Cobrar (Neto) | B7: ='Estados Financieros (Datos)'!B7 | C7: ='Estados Financieros (Datos)'!C7
A8: Inventarios | B8: ='Estados Financieros (Datos)'!B8 | C8: ='Estados Financieros (Datos)'!C8
A9: Terrenos y Edificios (Neto) | B9: ='Estados Financieros (Datos)'!B11 | C9: ='Estados Financieros (Datos)'!C11
A10: Maquinaria y Equipos (Neto) | B10: ='Estados Financieros (Datos)'!B12 | C10: ='Estados Financieros (Datos)'!C12
A11: TOTAL ACTIVO | B11: ='Estados Financieros (Datos)'!B19 | C11: ='Estados Financieros (Datos)'!C19
A14: UNIDAD 1 Y 3: TABLA DE RATIOS E INDICADORES CLAVE (AÑO 2)
A15: Ratio / Indicador Financiero | B15: Fórmula del Indicador | C15: Resultado Estudiante | D15: Valor Objetivo | E15: Evaluación / Dictamen
A16: Razón Corriente (Liquidez General) | B16: Activo Corriente / Pasivo Corriente | D16: 1,50 - 2,50
A17: Prueba Ácida (Liquidez Severa) | B17: (Activo Corriente - Inventarios) / Pasivo Corriente | D17: 1,00 - 1,50
A18: Liquidez Inmediata (Efectivo en Bancos) | B18: Efectivo y Equivalentes / Pasivo Corriente | D18: 0,30 - 0,50
A19: Ratio de Endeudamiento Total | B19: (Pasivo Total / Activo Total) * 100 | D19: <= 60,00%
A20: Período Medio de Cobro (PMC) | B20: (Cuentas por Cobrar Promedio / Ventas) * 365 | D20: < PMP
A21: Días Promedio de Inventario (DPI) | B21: (Inventario Promedio / Costo Ventas) * 365 | D21: Optimizados
A22: Punto de Equilibrio en BS (Ve) | B22: Costos Fijos Totales / Ratio Margen Contribución | D22: Cobertura 100%
A23: Punto de Equilibrio en Unidades (Qe) | B23: Costos Fijos Totales / Margen Contribución Unitario | D23: Cobertura 100%
A24: ROA (Rendimiento del Activo) | B24: Utilidad Neta / Activo Total Promedio | D24: > 10,00%
A25: ROE (Rentabilidad del Patrimonio) | B25: Utilidad Neta / Patrimonio Promedio | D25: > Costo Capital

Sheet Solucionario Docente
A1: SOLUCIONARIO DOCENTE Y CLAVE DE RESPUESTAS (FÓRMULAS ACTIVAS)
A2: Uso exclusivo del Facilitador (Prof. MSc. Frank Clemente)
A4: 1. SOLUCIÓN ANÁLISIS VERTICAL Y HORIZONTAL DE ACTIVOS
A5: Cuenta de Activo | B5: Año 1 (BS) | C5: Año 2 (BS) | D5: % Vertical (Año 2) | E5: Δ Absoluta (BS) | F5: % Variación Horizontal
A6: Efectivo y Equivalentes | B6: ='Estados Financieros (Datos)'!B6 | C6: ='Estados Financieros (Datos)'!C6 | D6: =C6/'Estados Financieros (Datos)'!C19 | E6: =C6-B6 | F6: =(C6-B6)/B6
A7: Cuentas por Cobrar (Neto) | B7: ='Estados Financieros (Datos)'!B7 | C7: ='Estados Financieros (Datos)'!C7 | D7: =C7/'Estados Financieros (Datos)'!C19 | E7: =C7-B7 | F7: =(C7-B7)/B7
A8: Inventarios | B8: ='Estados Financieros (Datos)'!B8 | C8: ='Estados Financieros (Datos)'!C8 | D8: =C8/'Estados Financieros (Datos)'!C19 | E8: =C8-B8 | F8: =(C8-B8)/B8
A9: Terrenos y Edificios (Neto) | B9: ='Estados Financieros (Datos)'!B11 | C9: ='Estados Financieros (Datos)'!C11 | D9: =C9/'Estados Financieros (Datos)'!C19 | E9: =C9-B9 | F9: =(C9-B9)/B9
A10: Maquinaria y Equipos (Neto) | B10: ='Estados Financieros (Datos)'!B12 | C10: ='Estados Financieros (Datos)'!C12 | D10: =C10/'Estados Financieros (Datos)'!C19 | E10: =C10-B10 | F10: =(C10-B10)/B10
A11: TOTAL ACTIVO | B11: ='Estados Financieros (Datos)'!B19 | C11: ='Estados Financieros (Datos)'!C19 | D11: =C11/'Estados Financieros (Datos)'!C19 | E11: =C11-B11 | F11: =(C11-B11)/B11
A14: 2. SOLUCIÓN DE RATIOS E INDICADORES CLAVE (FÓRMULAS ACTIVAS)
A15: Ratio / Indicador Financiero | B15: Fórmula del Indicador | C15: Resultado Calculado | D15: Valor Objetivo | E15: Dictamen Técnico Docente
A16: Razón Corriente (Liquidez General) | B16: Activo Corriente / Pasivo Corriente | C16: ='Estados Financieros (Datos)'!C9 / 'Estados Financieros (Datos)'!F9 | D16: 1,50 - 2,50 | E16: Solvente pero inflada por inventarios ilíquidos
A17: Prueba Ácida (Liquidez Severa) | B17: (Activo Corriente - Inventarios) / Pasivo Corriente | C17: =('Estados Financieros (Datos)'!C9 - 'Estados Financieros (Datos)'!C8) / 'Estados Financieros (Datos)'!F9 | D17: 1,00 - 1,50 | E17: Déficit severo de liquidez (0.93 BS por cada 1 BS de deuda)
A18: Liquidez Inmediata (Efectivo Real) | B18: Efectivo y Equivalentes / Pasivo Corriente | C18: ='Estados Financieros (Datos)'!C6 / 'Estados Financieros (Datos)'!F9 | D18: 0,30 - 0,50 | E18: CRÍTICO: Solo cubre el 1,8% de las deudas en banco
A19: Ratio de Endeudamiento Total | B19: (Pasivo Total / Activo Total) * 100 | C19: ='Estados Financieros (Datos)'!F13 / 'Estados Financieros (Datos)'!C19 | D19: <= 60,00% | E19: Saludable (38,35% de los activos financiados por terceros)
A20: Período Medio de Cobro (PMC) | B20: (Cuentas por Cobrar Promedio / Ventas) * 365 | C20: =(AVERAGE('Estados Financieros (Datos)'!B7,'Estados Financieros (Datos)'!C7) / 'Estados Financieros (Datos)'!C24) * 365 | D20: < PMP | E20: Laxo: Tarda 43 días promedio en cobrar (65 días al cierre)
A21: Punto de Equilibrio en BS (Ve) | B21: Costos Fijos Totales / Ratio Margen Contribución | C21: =(210000 + 35000) / ((1400000 - 950000) / 1400000) | D21: Cobertura 100% | E21: Excelente: Requiere 762.222 BS de ventas (Vende 1,4 Millones)
A22: ROA (Rendimiento del Activo) | B22: Utilidad Neta / Activo Total Promedio | C22: ='Estados Financieros (Datos)'!C33 / AVERAGE('Estados Financieros (Datos)'!B19,'Estados Financieros (Datos)'!C19) | D22: > 10,00% | E22: Excelente eficiencia de activos (14,36%)
A23: ROE (Rentabilidad del Patrimonio) | B23: Utilidad Neta / Patrimonio Promedio | C23: ='Estados Financieros (Datos)'!C33 / AVERAGE('Estados Financieros (Datos)'!E18,'Estados Financieros (Datos)'!F18) | D23: > Costo Capital | E23: Sobresaliente retorno a los accionistas (22,70%)
